ThLun/__init__.py
ThLun/io/__init__.py
ThLun/io/_output.py
ThLun/io/io.py
ThLun/io/ansi/__init__.py
ThLun/io/ansi/screen.py
ThLun/io/ansi/styles.py
ThLun/logger/__init__.py
ThLun/logger/logger.py
ThLun/logger/types.py
ThLun/progress/__init__.py
ThLun/progress/bar.py
ThLun/spinner/__init__.py
ThLun/spinner/spinner.py
ThLun/spinner/spinners.py
thlun-0.1.3.dist-info/licenses/LICENSE
thlun-0.1.3.dist-info/METADATA
thlun-0.1.3.dist-info/WHEEL
thlun-0.1.3.dist-info/top_level.txt
thlun-0.1.3.dist-info/RECORD
