Metadata-Version: 2.4
Name: thlun
Version: 0.1.3
Summary: CLI library
Author: Ashreach
Maintainer: Netronis, Rastgame
License-Expression: Apache-2.0
Project-URL: Homepage, https://github.com/Ashreach/ThLun
Project-URL: Source, https://github.com/Ashreach/ThLun
Project-URL: Organization, https://github.com/Ashreach
Requires-Python: >=3.9
License-File: LICENSE
Provides-Extra: dev
Requires-Dist: pytest>=8.4.2; extra == "dev"
Requires-Dist: ruff>=0.6.9; extra == "dev"
Requires-Dist: mypy>=1.11.2; extra == "dev"
Requires-Dist: build>=1.3.0; extra == "dev"
Requires-Dist: twine>=6.2.0; extra == "dev"
Provides-Extra: docs
Requires-Dist: mkdocs>=1.6.1; extra == "docs"
Requires-Dist: mkdocs-autorefs>=1.4.3; extra == "docs"
Requires-Dist: mkdocs-git-revision-date-localized-plugin>=1.5.0; extra == "docs"
Requires-Dist: mkdocs-material>=9.6.23; extra == "docs"
Requires-Dist: mkdocs-minify-plugin>=0.8.0; extra == "docs"
Requires-Dist: mkdocstrings[python]>=0.30.1; extra == "docs"
Dynamic: license-file
